libspitz/Args.py
libspitz/Blob.py
libspitz/ClientEndpoint.py
libspitz/Endpoint.py
libspitz/JobBinary.py
libspitz/Listener.py
libspitz/LogUtils.py
libspitz/PerfModule.py
libspitz/Pointer.py
libspitz/Result.py
libspitz/SimpleEndpoint.py
libspitz/TaskPool.py
libspitz/Timeout.py
libspitz/UIDUtils.py
libspitz/__init__.py
libspitz/memstat.py
libspitz/config/__init__.py
libspitz/messaging/MessagingError.py
libspitz/messaging/SocketClosed.py
libspitz/messaging/__init__.py
py_pits-0.0.1.data/scripts/pypits-examples
py_pits-0.0.1.data/scripts/pypits-gen-api
py_pits-0.0.1.data/scripts/pypits-jm
py_pits-0.0.1.data/scripts/pypits-tm
py_pits-0.0.1.dist-info/LICENSE
py_pits-0.0.1.dist-info/METADATA
py_pits-0.0.1.dist-info/WHEEL
py_pits-0.0.1.dist-info/top_level.txt
py_pits-0.0.1.dist-info/RECORD
